[
  {
    "full_name": "sonigy/YCS",
    "stargazers_count": 56,
    "open_issues_count": 8,
    "forks_count": 3
  },
  {
    "full_name": "logto-io/logto",
    "stargazers_count": 5254,
    "open_issues_count": 64,
    "forks_count": 185
  },
  {
    "full_name": "gitpod-io/workspace-images",
    "stargazers_count": 415,
    "open_issues_count": 58,
    "forks_count": 326
  },
  {
    "full_name": "open-sauced/open-sauced",
    "stargazers_count": 840,
    "open_issues_count": 9,
    "forks_count": 518
  }
]