[
  {
    "full_name": "sonigy/YCS",
    "stargazers_count": 41,
    "open_issues_count": 6,
    "forks_count": 2
  },
  {
    "full_name": "logto-io/logto",
    "stargazers_count": 4652,
    "open_issues_count": 54,
    "forks_count": 136
  },
  {
    "full_name": "gitpod-io/workspace-images",
    "stargazers_count": 392,
    "open_issues_count": 38,
    "forks_count": 297
  },
  {
    "full_name": "open-sauced/open-sauced",
    "stargazers_count": 804,
    "open_issues_count": 18,
    "forks_count": 413
  }
]