[
  {
    "full_name": "sonigy/YCS",
    "stargazers_count": 101,
    "open_issues_count": 17,
    "forks_count": 4
  },
  {
    "full_name": "logto-io/logto",
    "stargazers_count": 7943,
    "open_issues_count": 135,
    "forks_count": 393
  },
  {
    "full_name": "gitpod-io/workspace-images",
    "stargazers_count": 469,
    "open_issues_count": 52,
    "forks_count": 316
  },
  {
    "full_name": "open-sauced/open-sauced",
    "stargazers_count": 925,
    "open_issues_count": 0,
    "forks_count": 942
  }
]