[
  {
    "full_name": "ethereum-lists/chains",
    "stargazers_count": 7975,
    "open_issues_count": 122,
    "forks_count": 5480
  },
  {
    "full_name": "microsoft/garnet",
    "stargazers_count": 7463,
    "open_issues_count": 32,
    "forks_count": 315
  },
  {
    "full_name": "CISOfy/lynis",
    "stargazers_count": 12388,
    "open_issues_count": 159,
    "forks_count": 1381
  },
  {
    "full_name": "Stability-AI/generative-models",
    "stargazers_count": 21631,
    "open_issues_count": 246,
    "forks_count": 2341
  },
  {
    "full_name": "microsoft/generative-ai-for-beginners",
    "stargazers_count": 31822,
    "open_issues_count": 19,
    "forks_count": 18851
  },
  {
    "full_name": "doubleangels/NextDNSManager",
    "stargazers_count": 191,
    "open_issues_count": 0,
    "forks_count": 9
  },
  {
    "full_name": "dahlia/fedify",
    "stargazers_count": 139,
    "open_issues_count": 4,
    "forks_count": 5
  },
  {
    "full_name": "electric-capital/crypto-ecosystems",
    "stargazers_count": 1261,
    "open_issues_count": 43,
    "forks_count": 1080
  },
  {
    "full_name": "fluencelabs/dev-rewards",
    "stargazers_count": 465,
    "open_issues_count": 11,
    "forks_count": 296
  },
  {
    "full_name": "cloudflare/pingora",
    "stargazers_count": 17995,
    "open_issues_count": 78,
    "forks_count": 965
  },
  {
    "full_name": "ironicbadger/infra",
    "stargazers_count": 673,
    "open_issues_count": 0,
    "forks_count": 39
  },
  {
    "full_name": "gerardog/gsudo",
    "stargazers_count": 4690,
    "open_issues_count": 31,
    "forks_count": 125
  },
  {
    "full_name": "fingerprintjs/BotD",
    "stargazers_count": 882,
    "open_issues_count": 4,
    "forks_count": 73
  },
  {
    "full_name": "github/evergreen",
    "stargazers_count": 108,
    "open_issues_count": 12,
    "forks_count": 7
  },
  {
    "full_name": "mchangrh/sb-mirror",
    "stargazers_count": 151,
    "open_issues_count": 13,
    "forks_count": 22
  },
  {
    "full_name": "ajayyy/SponsorBlock",
    "stargazers_count": 8585,
    "open_issues_count": 293,
    "forks_count": 280
  },
  {
    "full_name": "ajayyy/DeArrow",
    "stargazers_count": 930,
    "open_issues_count": 69,
    "forks_count": 29
  },
  {
    "full_name": "WordPress/wordpress-develop",
    "stargazers_count": 2251,
    "open_issues_count": 1391,
    "forks_count": 2282
  },
  {
    "full_name": "WordPress/wporg-two-factor",
    "stargazers_count": 23,
    "open_issues_count": 56,
    "forks_count": 5
  },
  {
    "full_name": "denoland/denokv",
    "stargazers_count": 377,
    "open_issues_count": 15,
    "forks_count": 14
  },
  {
    "full_name": "flathub-infra/website",
    "stargazers_count": 183,
    "open_issues_count": 83,
    "forks_count": 75
  },
  {
    "full_name": "stefansundin/2fa-qr",
    "stargazers_count": 201,
    "open_issues_count": 0,
    "forks_count": 77
  },
  {
    "full_name": "tildeverse/mastodon",
    "stargazers_count": 5,
    "open_issues_count": 0,
    "forks_count": 0
  },
  {
    "full_name": "steplix/emv-qrcps",
    "stargazers_count": 16,
    "open_issues_count": 1,
    "forks_count": 11
  },
  {
    "full_name": "pimoroni/badger2040",
    "stargazers_count": 123,
    "open_issues_count": 39,
    "forks_count": 43
  },
  {
    "full_name": "mautrix/gmessages",
    "stargazers_count": 61,
    "open_issues_count": 6,
    "forks_count": 6
  },
  {
    "full_name": "rgerum/unofficial-duolingo-stories",
    "stargazers_count": 116,
    "open_issues_count": 15,
    "forks_count": 28
  },
  {
    "full_name": "gittuf/gittuf",
    "stargazers_count": 313,
    "open_issues_count": 49,
    "forks_count": 19
  },
  {
    "full_name": "microsoft/devhome",
    "stargazers_count": 3222,
    "open_issues_count": 444,
    "forks_count": 244
  },
  {
    "full_name": "Podcastindex-org/podcast-namespace",
    "stargazers_count": 356,
    "open_issues_count": 94,
    "forks_count": 108
  }
]