[
  {
    "full_name": "LazyVim/LazyVim",
    "stargazers_count": 9552,
    "open_issues_count": 17,
    "forks_count": 645
  },
  {
    "full_name": "dsherret/dax",
    "stargazers_count": 406,
    "open_issues_count": 26,
    "forks_count": 21
  },
  {
    "full_name": "asdf-community/asdf-direnv",
    "stargazers_count": 471,
    "open_issues_count": 2,
    "forks_count": 36
  },
  {
    "full_name": "asdf-vm/asdf-plugins",
    "stargazers_count": 986,
    "open_issues_count": 24,
    "forks_count": 405
  },
  {
    "full_name": "crazy-max/diun",
    "stargazers_count": 2211,
    "open_issues_count": 48,
    "forks_count": 98
  },
  {
    "full_name": "tailscale-dev/vscode-tailscale",
    "stargazers_count": 45,
    "open_issues_count": 52,
    "forks_count": 1
  },
  {
    "full_name": "SteamRE/SteamKit",
    "stargazers_count": 2335,
    "open_issues_count": 51,
    "forks_count": 465
  },
  {
    "full_name": "PonyvilleFM/aura",
    "stargazers_count": 36,
    "open_issues_count": 6,
    "forks_count": 7
  },
  {
    "full_name": "Xe/waifud",
    "stargazers_count": 141,
    "open_issues_count": 16,
    "forks_count": 5
  },
  {
    "full_name": "qpdf/qpdf",
    "stargazers_count": 2694,
    "open_issues_count": 165,
    "forks_count": 229
  },
  {
    "full_name": "pikepdf/pikepdf",
    "stargazers_count": 1881,
    "open_issues_count": 40,
    "forks_count": 170
  },
  {
    "full_name": "snoonetIRC/website",
    "stargazers_count": 3,
    "open_issues_count": 7,
    "forks_count": 6
  },
  {
    "full_name": "asciinema/asciinema-player",
    "stargazers_count": 2490,
    "open_issues_count": 17,
    "forks_count": 261
  },
  {
    "full_name": "ihabunek/toot",
    "stargazers_count": 1017,
    "open_issues_count": 94,
    "forks_count": 103
  },
  {
    "full_name": "fontsource/font-files",
    "stargazers_count": 60,
    "open_issues_count": 20,
    "forks_count": 12
  },
  {
    "full_name": "star-history/star-history",
    "stargazers_count": 4987,
    "open_issues_count": 18,
    "forks_count": 240
  },
  {
    "full_name": "casbin/casbin",
    "stargazers_count": 15860,
    "open_issues_count": 34,
    "forks_count": 1625
  },
  {
    "full_name": "casdoor/casdoor",
    "stargazers_count": 7199,
    "open_issues_count": 115,
    "forks_count": 873
  },
  {
    "full_name": "bashtage/sphinx-material",
    "stargazers_count": 292,
    "open_issues_count": 37,
    "forks_count": 90
  },
  {
    "full_name": "ajhalili2006/personal-trauma-therapy-notebook",
    "stargazers_count": 1,
    "open_issues_count": 0,
    "forks_count": 0
  },
  {
    "full_name": "sindresorhus/legal-notices",
    "stargazers_count": 127,
    "open_issues_count": 0,
    "forks_count": 2
  },
  {
    "full_name": "privacyradius/gdpr-tracker",
    "stargazers_count": 173,
    "open_issues_count": 13,
    "forks_count": 68
  },
  {
    "full_name": "basecamp/audits1984",
    "stargazers_count": 280,
    "open_issues_count": 6,
    "forks_count": 16
  },
  {
    "full_name": "disclose/research-threats",
    "stargazers_count": 250,
    "open_issues_count": 17,
    "forks_count": 20
  },
  {
    "full_name": "basecamp/policies",
    "stargazers_count": 1892,
    "open_issues_count": 0,
    "forks_count": 265
  },
  {
    "full_name": "osano/cookieconsent",
    "stargazers_count": 3277,
    "open_issues_count": 91,
    "forks_count": 592
  },
  {
    "full_name": "ciarrocki/LibreLaw",
    "stargazers_count": 18,
    "open_issues_count": 0,
    "forks_count": 1
  },
  {
    "full_name": "canokaue/nft-music-license",
    "stargazers_count": 27,
    "open_issues_count": 0,
    "forks_count": 4
  },
  {
    "full_name": "oprvc/oprvc.github.io",
    "stargazers_count": 60,
    "open_issues_count": 4,
    "forks_count": 12
  },
  {
    "full_name": "ankane/awesome-legal",
    "stargazers_count": 649,
    "open_issues_count": 0,
    "forks_count": 40
  }
]